Metadata-Version: 1.1
Name: gt2-test-runner
Version: 1.0
Summary: unittest test runner with colourised output and per-test coverage support
Home-page: https://github.com/gt2-io/GT2-io/gt2-test-runner
Author: Gergely Polonkai
Author-email: gergo@gt2.io
License: MIT
Platform: UNKNOWN
Classifier: Intended Audience :: Developers
Classifier: License :: OSI Approved :: MIT License
Classifier: Operating System :: OS Independent
Classifier: Programming Language :: Python
Classifier: Programming Language :: Python :: 3
Classifier: Programming Language :: Python :: 3.4
Classifier: Programming Language :: Python :: 3.5
Classifier: Programming Language :: Python :: 3.6
